{
  "project_info": {
    "project_number": "843975186599",
    "project_id": "uni-45f5d",
    "storage_bucket": "uni-45f5d.firebasestorage.app"
  },
  "client": [
    {
      "client_info": {
        "mobilesdk_app_id": "1:843975186599:android:5c1f27fde13f10e1b2a382",
        "android_client_info": {
          "package_name": "com.example.flutterdersproje"
        }
      },
      "oauth_client": [],
      "api_key": [
        {
          "current_key": "AIzaSyCWObEovIGN___ynqE2yVCpFTLMWAnIF3w"
        }
      ],
      "services": {
        "appinvite_service": {
          "other_platform_oauth_client": []
        }
      }
    }
  ],
  "configuration_version": "1"
}